{
  "swagger": "2.0",
  "info": {
    "version": "1.0.0",
    "title": "Auto generated",
    "license": {
      "name": "MIT"
    }
  },
  "host": "petstore.swagger.io",
  "basePath": "/v1",
  "schemes": [
    "http"
  ],
  "consumes": [
    "application/json"
  ],
  "produces": [
    "application/json"
  ],
  "paths": {
    "/": {
      "get": {
        "responses": {
          "200": {
            "description": "200 response",
            "schema": {
              "$ref": "swagger/schemas/core/str.json"
            }
          },
          "404": {
            "description": "not found",
            "schema": {
              "$ref": "swagger/schemas/errors/404.json"
            }
          }
        },
        "summary": "empty",
        "parameters": []
      }
    },
    "/users/{email}/role/{role_name}": {
      "get": {
        "responses": {
          "200": {
            "description": "200 response",
            "schema": {
              "$ref": "swagger/schemas/core/user.json"
            }
          },
          "404": {
            "description": "not found",
            "schema": {
              "$ref": "swagger/schemas/errors/404.json"
            }
          }
        },
        "summary": "empty",
        "parameters": [
          {
            "name": "email",
            "in": "path",
            "required": true,
            "type": "string",
            "description": "Docstring"
          },
          {
            "name": "role_name",
            "in": "path",
            "required": true,
            "type": "string",
            "description": "Docstring"
          }
        ]
      }
    },
    "/users/{email}/role/{role_name}/remove": {
      "delete": {
        "responses": {
          "200": {
            "description": "200 response",
            "schema": {
              "$ref": "swagger/schemas/core/user.json"
            }
          },
          "404": {
            "description": "not found",
            "schema": {
              "$ref": "swagger/schemas/errors/404.json"
            }
          }
        },
        "summary": "empty",
        "parameters": [
          {
            "name": "email",
            "in": "path",
            "required": true,
            "type": "string",
            "description": "Docstring"
          },
          {
            "name": "role_name",
            "in": "path",
            "required": true,
            "type": "string",
            "description": "Docstring"
          }
        ]
      },
      "get": {
        "responses": {
          "200": {
            "description": "200 response",
            "schema": {
              "$ref": "swagger/schemas/core/user.json"
            }
          },
          "404": {
            "description": "not found",
            "schema": {
              "$ref": "swagger/schemas/errors/404.json"
            }
          }
        },
        "summary": "empty",
        "parameters": [
          {
            "name": "email",
            "in": "path",
            "required": true,
            "type": "string",
            "description": "Docstring"
          },
          {
            "name": "role_name",
            "in": "path",
            "required": true,
            "type": "string",
            "description": "Docstring"
          }
        ]
      }
    },
    "/role/create/{bl}/{appstackcode}/{env}/{perm_group}": {
      "post": {
        "responses": {
          "200": {
            "description": "200 response",
            "schema": {
              "$ref": "swagger/schemas/core/role.json"
            }
          },
          "404": {
            "description": "not found",
            "schema": {
              "$ref": "swagger/schemas/errors/404.json"
            }
          }
        },
        "summary": "empty",
        "parameters": [
          {
            "name": "bl",
            "in": "path",
            "required": true,
            "type": "string",
            "description": "Docstring"
          },
          {
            "name": "appstackcode",
            "in": "path",
            "required": true,
            "type": "string",
            "description": "Docstring"
          },
          {
            "name": "perm_group",
            "in": "path",
            "required": true,
            "type": "string",
            "description": "Docstring"
          },
          {
            "name": "env",
            "in": "path",
            "required": true,
            "type": "string",
            "description": "Docstring"
          }
        ]
      },
      "get": {
        "responses": {
          "200": {
            "description": "200 response",
            "schema": {
              "$ref": "swagger/schemas/core/role.json"
            }
          },
          "404": {
            "description": "not found",
            "schema": {
              "$ref": "swagger/schemas/errors/404.json"
            }
          }
        },
        "summary": "empty",
        "parameters": [
          {
            "name": "bl",
            "in": "path",
            "required": true,
            "type": "string",
            "description": "Docstring"
          },
          {
            "name": "appstackcode",
            "in": "path",
            "required": true,
            "type": "string",
            "description": "Docstring"
          },
          {
            "name": "perm_group",
            "in": "path",
            "required": true,
            "type": "string",
            "description": "Docstring"
          },
          {
            "name": "env",
            "in": "path",
            "required": true,
            "type": "string",
            "description": "Docstring"
          }
        ]
      }
    },
    "/users/{email}/invite": {
      "get": {
        "responses": {
          "200": {
            "description": "200 response",
            "schema": {
              "$ref": "swagger/schemas/core/user.json"
            }
          },
          "404": {
            "description": "not found",
            "schema": {
              "$ref": "swagger/schemas/errors/404.json"
            }
          }
        },
        "summary": "empty",
        "parameters": [
          {
            "name": "email",
            "in": "path",
            "required": true,
            "type": "string",
            "description": "Docstring"
          }
        ]
      }
    },
    "/users": {
      "get": {
        "responses": {
          "200": {
            "description": "200 response",
            "schema": {
              "$ref": "swagger/schemas/core/user.json"
            }
          },
          "404": {
            "description": "not found",
            "schema": {
              "$ref": "swagger/schemas/errors/404.json"
            }
          }
        },
        "summary": "empty",
        "parameters": []
      }
    },
    "/users/{email}": {
      "get": {
        "responses": {
          "200": {
            "description": "200 response",
            "schema": {
              "$ref": "swagger/schemas/core/user.json"
            }
          },
          "404": {
            "description": "not found",
            "schema": {
              "$ref": "swagger/schemas/errors/404.json"
            }
          }
        },
        "summary": "empty",
        "parameters": [
          {
            "name": "email",
            "in": "path",
            "required": true,
            "type": "string",
            "description": "Docstring"
          }
        ]
      }
    },
    "/users/{email}/complete": {
      "get": {
        "responses": {
          "200": {
            "description": "200 response",
            "schema": {
              "$ref": "swagger/schemas/core/user.json"
            }
          },
          "404": {
            "description": "not found",
            "schema": {
              "$ref": "swagger/schemas/errors/404.json"
            }
          }
        },
        "summary": "empty",
        "parameters": [
          {
            "name": "email",
            "in": "path",
            "required": true,
            "type": "string",
            "description": "Docstring"
          }
        ]
      }
    },
    "/roles": {
      "get": {
        "responses": {
          "200": {
            "description": "200 response",
            "schema": {
              "$ref": "swagger/schemas/core/role.json"
            }
          },
          "404": {
            "description": "not found",
            "schema": {
              "$ref": "swagger/schemas/errors/404.json"
            }
          }
        },
        "summary": "empty",
        "parameters": []
      }
    },
    "/permissions_groups": {
      "get": {
        "responses": {
          "200": {
            "description": "200 response",
            "schema": {
              "$ref": "swagger/schemas/core/str.json"
            }
          },
          "404": {
            "description": "not found",
            "schema": {
              "$ref": "swagger/schemas/errors/404.json"
            }
          }
        },
        "summary": "empty",
        "parameters": []
      }
    }
  }
}